pypechain/__init__.py
pypechain/main.py
pypechain/core/__init__.py
pypechain/core/base_event.py
pypechain/core/combomethod_typed.py
pypechain/core/contract_call_exception.py
pypechain/core/contract_function.py
pypechain/core/error.py
pypechain/core/utilities.py
pypechain/core/utilities_test.py
pypechain/foundry/types.py
pypechain/foundry/utilities.py
pypechain/hardhat/types.py
pypechain/hardhat/utilities.py
pypechain/render/__init__.py
pypechain/render/contract.py
pypechain/render/contract_test.py
pypechain/render/init.py
pypechain/render/init_test.py
pypechain/render/render.py
pypechain/render/types.py
pypechain/solc/types.py
pypechain/solc/utilities.py
pypechain/templates/init.py.jinja2
pypechain/templates/types.py.jinja2
pypechain/templates/contract.py/abi.py.jinja2
pypechain/templates/contract.py/base.py.jinja2
pypechain/templates/contract.py/contract.py.jinja2
pypechain/templates/contract.py/errors.py.jinja2
pypechain/templates/contract.py/events.py.jinja2
pypechain/templates/contract.py/functions.py.jinja2
pypechain/test/__init__.py
pypechain/test/test_file_recursion.py
pypechain/test/deploy_linking/__init__.py
pypechain/test/deploy_linking/test_deploy_linking.py
pypechain/test/deploy_linking/abis/Contract.sol/Contract.json
pypechain/test/deploy_linking/abis/MyLibrary.sol/MyLibrary.json
pypechain/test/deploy_linking/abis/build-info/86900092972ca4a4cee7ad68b366fd29.json
pypechain/test/deploy_linking/contracts/Contract.sol
pypechain/test/deploy_linking/contracts/MyLibrary.sol
pypechain/test/deploy_linking/types/__init__.py
pypechain/test/deploy_linking/types/pypechain.version
pypechain/test/deploy_linking/types/Contract/ContractContract.py
pypechain/test/deploy_linking/types/Contract/__init__.py
pypechain/test/deploy_linking/types/MyLibrary/MyLibraryContract.py
pypechain/test/deploy_linking/types/MyLibrary/__init__.py
pypechain/test/deployment/__init__.py
pypechain/test/deployment/test_deployment.py
pypechain/test/deployment/abis/ConstructorNoArgs.sol/ConstructorNoArgs.json
pypechain/test/deployment/abis/build-info/9d6ae9a9e3a305b175590fc5abcd507a.json
pypechain/test/errors/abis/build-info/ba6c09394468f987bf5f2a5de8d8c3a9.json
pypechain/test/events/abis/build-info/872a51ef2e57c9ca0469bceb563f5548.json
pypechain/test/events/abis/build-info/e87689b29f4c9ef5c7f3df2eca29ba02.json
pypechain/test/overloading/abis/build-info/743f0eefae5edb17cf848f02c85e0e3a.json
pypechain/test/return_types/abis/build-info/dff2551eff6ca91ba1ea5090bfa3f965.json
pypechain/test/sign_and_transact/abis/build-info/89a3ccfd9743746713afb7125abb9c8e.json
pypechain/test/struct_references/abis/build-info/34f9735d141b517851f955e4981e1a16.json
pypechain/test/struct_references/abis/build-info/6be3175dcba54a139d6612854a334628.json
pypechain/test/structs/abis/build-info/3aa33e001391f4d70c5ae1642da1096a.json
pypechain-0.0.49.dist-info/entry_points.txt
pypechain-0.0.49.dist-info/LICENSE
pypechain-0.0.49.dist-info/WHEEL
pypechain-0.0.49.dist-info/METADATA
pypechain-0.0.49.dist-info/RECORD
