Metadata-Version: 2.3
Name: pypechain
Version: 0.0.49
Summary: Codegen python interfaces for web3.py contracts.
Author-email: Matthew Brown <matt@delv.tech>, Dylan Paiton <dylan@delv.tech>, Sheng Lundquist <sheng@delv.tech>, Mihai Cosma <mihai@delv.tech>
Requires-Python: >=3.10
Classifier: Programming Language :: Python :: 3
Classifier: License :: OSI Approved :: Apache Software License
Classifier: Operating System :: OS Independent
Requires-Dist: autoflake
Requires-Dist: black
Requires-Dist: eth-account >= 0.13.3
Requires-Dist: eth-typing >= 5.0.0
Requires-Dist: isort
Requires-Dist: jinja2
Requires-Dist: toml
Requires-Dist: web3 == 7.6
Requires-Dist: pypechain[test, build] ; extra == "all"
Requires-Dist: build ; extra == "build"
Requires-Dist: flit ; extra == "build"
Requires-Dist: requests ; extra == "build"
Requires-Dist: setuptools ; extra == "build"
Requires-Dist: toml ; extra == "build"
Requires-Dist: twine ; extra == "build"
Requires-Dist: wheel ; extra == "build"
Requires-Dist: coverage ; extra == "test"
Requires-Dist: factory-boy ; extra == "test"
Requires-Dist: pylint ; extra == "test"
Requires-Dist: pyright ; extra == "test"
Requires-Dist: pytest ; extra == "test"
Requires-Dist: pytest-snapshot ; extra == "test"
Project-URL: Bug Tracker, https://github.com/delvtech/pypechain/issues
Project-URL: Homepage, https://github.com/delvtech/pypechain
Provides-Extra: all
Provides-Extra: build
Provides-Extra: test
